masakarimonitors/__init__.py
masakarimonitors/config.py
masakarimonitors/i18n.py
masakarimonitors/manager.py
masakarimonitors/privsep.py
masakarimonitors/service.py
masakarimonitors/utils.py
masakarimonitors/version.py
masakarimonitors/cmd/__init__.py
masakarimonitors/cmd/hostmonitor.py
masakarimonitors/cmd/instancemonitor.py
masakarimonitors/cmd/introspectiveinstancemonitor.py
masakarimonitors/cmd/processmonitor.py
masakarimonitors/common/__init__.py
masakarimonitors/common/config.py
masakarimonitors/conf/__init__.py
masakarimonitors/conf/api.py
masakarimonitors/conf/base.py
masakarimonitors/conf/consul.py
masakarimonitors/conf/host.py
masakarimonitors/conf/instance.py
masakarimonitors/conf/introspectiveinstancemonitor.py
masakarimonitors/conf/kubernetes.py
masakarimonitors/conf/opts.py
masakarimonitors/conf/process.py
masakarimonitors/conf/service.py
masakarimonitors/ha/__init__.py
masakarimonitors/ha/masakari.py
masakarimonitors/hacking/__init__.py
masakarimonitors/hacking/checks.py
masakarimonitors/hostmonitor/__init__.py
masakarimonitors/hostmonitor/driver.py
masakarimonitors/hostmonitor/host.py
masakarimonitors/hostmonitor/consul_check/__init__.py
masakarimonitors/hostmonitor/consul_check/consul_helper.py
masakarimonitors/hostmonitor/consul_check/manager.py
masakarimonitors/hostmonitor/consul_check/matrix_helper.py
masakarimonitors/hostmonitor/host_handler/__init__.py
masakarimonitors/hostmonitor/host_handler/handle_host.py
masakarimonitors/hostmonitor/host_handler/hold_host_status.py
masakarimonitors/hostmonitor/host_handler/parse_cib_xml.py
masakarimonitors/hostmonitor/host_handler/parse_crmmon_xml.py
masakarimonitors/hostmonitor/kubernetes_check/__init__.py
masakarimonitors/hostmonitor/kubernetes_check/manager.py
masakarimonitors/instancemonitor/__init__.py
masakarimonitors/instancemonitor/instance.py
masakarimonitors/instancemonitor/libvirt_handler/__init__.py
masakarimonitors/instancemonitor/libvirt_handler/callback.py
masakari_monitors-20.0.0.dist-info/AUTHORS
masakari_monitors-20.0.0.dist-info/LICENSE
masakari_monitors-20.0.0.dist-info/METADATA
masakari_monitors-20.0.0.dist-info/WHEEL
masakari_monitors-20.0.0.dist-info/entry_points.txt
masakari_monitors-20.0.0.dist-info/pbr.json
masakari_monitors-20.0.0.dist-info/top_level.txt
masakari_monitors-20.0.0.dist-info/RECORD
