Metadata-Version: 2.1
Name: masakari-monitors
Version: 20.0.0
Summary: Monitors for Masakari
Home-page: https://docs.openstack.org/masakari-monitors/latest/
Author: OpenStack
Author-email: openstack-dev@lists.openstack.org
License: Apache-2.0
Classifier: Environment :: OpenStack
Classifier: Intended Audience :: Information Technology
Classifier: Intended Audience :: System Administrators
Classifier: Operating System :: POSIX :: Linux
Classifier: Programming Language :: Python
Classifier: Programming Language :: Python :: Implementation :: CPython
Classifier: Programming Language :: Python :: 3 :: Only
Classifier: Programming Language :: Python :: 3
Classifier: Programming Language :: Python :: 3.10
Classifier: Programming Language :: Python :: 3.11
Classifier: Programming Language :: Python :: 3.12
Classifier: Programming Language :: Python :: 3.13
Requires-Python: >=3.10
License-File: LICENSE
License-File: AUTHORS
Requires-Dist: automaton >=1.9.0
Requires-Dist: keystoneauth1 >=3.4.0
Requires-Dist: openstacksdk >=0.13.0
Requires-Dist: oslo.concurrency >=3.26.0
Requires-Dist: oslo.config >=5.2.0
Requires-Dist: lxml >=4.5.0
Requires-Dist: oslo.cache >=1.26.0
Requires-Dist: oslo.i18n >=3.15.3
Requires-Dist: oslo.log >=3.36.0
Requires-Dist: oslo.middleware >=3.31.0
Requires-Dist: oslo.privsep >=1.23.0
Requires-Dist: oslo.service !=1.28.1,>=1.24.0
Requires-Dist: oslo.utils >=3.33.0
Requires-Dist: pbr !=2.1.0,>=2.0.0
Requires-Dist: python-consul >=1.1.0
Requires-Dist: kubernetes >=29.0.0
